figma_mcp_server/__init__.py
figma_mcp_server/cli.py
figma_mcp_server/figma_component_analyzer.py
figma_mcp_server/figma_frame_extractor.py
figma_mcp_server/figma_image_extractor.py
figma_mcp_server/figma_node_lister.py
figma_mcp_server/figma_roadmap_generator.py
figma_mcp_server/figma_smart_component_analyzer.py
figma_mcp_server/figma_text_extractor.py
figma_mcp_server/figma_tree_extractor.py
figma_mcp_server/file_saver.py
figma_mcp_server/server.py
figma_mcp_tools-1.0.13.dist-info/licenses/LICENSE
figma_mcp_tools-1.0.13.dist-info/METADATA
figma_mcp_tools-1.0.13.dist-info/WHEEL
figma_mcp_tools-1.0.13.dist-info/entry_points.txt
figma_mcp_tools-1.0.13.dist-info/top_level.txt
figma_mcp_tools-1.0.13.dist-info/RECORD
