Metadata-Version: 2.4
Name: figma-mcp-tools
Version: 1.0.13
Summary: A Model Context Protocol (MCP) server for Figma integration
Author-email: DRX-1877 <rdo198828@gmail.com>
Maintainer-email: DRX-1877 <rdo198828@gmail.com>
License: MIT
Project-URL: Homepage, https://github.com/DRX-1877/figma-mcp-server
Project-URL: Documentation, https://github.com/DRX-1877/figma-mcp-server#readme
Project-URL: Repository, https://github.com/DRX-1877/figma-mcp-server
Project-URL: Bug Tracker, https://github.com/DRX-1877/figma-mcp-server/issues
Keywords: figma,mcp,model-context-protocol,design,api
Classifier: Development Status :: 4 - Beta
Classifier: Intended Audience :: Developers
Classifier: License :: OSI Approved :: MIT License
Classifier: Operating System :: OS Independent
Classifier: Programming Language :: Python :: 3
Classifier: Programming Language :: Python :: 3.10
Classifier: Programming Language :: Python :: 3.11
Classifier: Programming Language :: Python :: 3.12
Requires-Python: >=3.10
License-File: LICENSE
Requires-Dist: mcp>=1.0.0
Requires-Dist: httpx>=0.24.0
Requires-Dist: requests>=2.28.0
Provides-Extra: dev
Requires-Dist: pytest>=7.0.0; extra == "dev"
Requires-Dist: black>=22.0.0; extra == "dev"
Requires-Dist: flake8>=5.0.0; extra == "dev"
Requires-Dist: mypy>=1.0.0; extra == "dev"
Dynamic: license-file
